{
    "os": "Linux-5.15.0-27-generic-x86_64-with-debian-bookworm-sid",
    "python": "3.7.6",
    "heartbeatAt": "2022-05-01T17:11:32.589127",
    "startedAt": "2022-05-01T17:11:31.217664",
    "docker": null,
    "gpu": "NVIDIA GeForce GTX 1060",
    "gpu_count": 1,
    "cpu_count": 8,
    "cuda": null,
    "args": [
        "--batch",
        "16",
        "--epochs",
        "10",
        "--data",
        "data/Dirt_Detection.yaml",
        "--weights",
        "weights/yolov5s.pt",
        "--cache"
    ],
    "state": "running",
    "program": "train.py",
    "codePath": "train.py",
    "git": {
        "remote": "git@github.com:Unistuttgart-As-Xu/Teamprojekt_test.git",
        "commit": "3a8e9bc557089f3ab09c5fad443b1407178a8efa"
    },
    "email": "tom1049443989@gmail.com",
    "root": "/home/zhenhaoxu/yolo/yolov5",
    "host": "zhenhaoxu-virtual-machine",
    "username": "zhenhaoxu",
    "executable": "/home/zhenhaoxu/anaconda3/bin/python"
}
